[
    {
        "question": "You are a math expert. When you respond, respond only with the Solution of the final Problem, thinking step by step. At the end of the Solution, when you give your final answer, write it in the form 'Final Answer: \\\\boxed{$answer$}. I hope it is correct.'\nFactor $58x^5-203x^{11}$.",
        "inference": "$58x^5-203x^{11} = x^5(58-203x^6)$\n\nFinal Answer: $\\boxed{x^5(58-203x^6)}$\n",
        "ground_truth": "Since $58=2\\cdot29$ and $203=7\\cdot29$, we can factor a $29x^5$ from the expression, to get $$58x^5-203x^{11}=\\boxed{-29x^5(7x^6-2)}.$$"
    },
    {
        "question": "$58x^5-203x^{11} = x^5(58-203x^6)$\n\nFinal Answer: $\\boxed{x^5(58-203x^6)}$\n\nThere might be an error in the solution above because of lack of understanding of the question. Please correct the error, if any, and rewrite the solution. Only output the final solution \\\\boxed{$answer$}. I hope it is correct.'",
        "inference": "$\\boxed{x^5(58-203x^6)}$\n",
        "ground_truth": "Since $58=2\\cdot29$ and $203=7\\cdot29$, we can factor a $29x^5$ from the expression, to get $$58x^5-203x^{11}=\\boxed{-29x^5(7x^6-2)}.$$"
    }
]