[
    {
        "question": "You are a math expert. When you respond, respond only with the Solution of the final Problem, thinking step by step. At the end of the Solution, when you give your final answer, write it in the form 'Final Answer: \\\\boxed{$answer$}. I hope it is correct.'\nWhich of the following functions have inverses?  Note that the domain of each function is also given.\n\nA. $a(x) = \\sqrt{2 - x},$ $x \\in (-\\infty,2].$\n\nB. $b(x) = x^3 - x,$ $x \\in \\mathbb{R}.$\n\nC. $c(x) = x + \\frac{1}{x},$ $x \\in (0,\\infty).$\n\nD. $d(x) = 2x^2 + 4x + 7,$ $x \\in [0,\\infty).$\n\nE. $e(x) = |x - 2| + |x + 3|,$ $x \\in \\mathbb{R}.$\n\nF. $f(x) = 3^x + 7^x,$ $x \\in \\mathbb{R}.$\n\nG. $g(x) = x - \\frac{1}{x},$ $x \\in (0,\\infty).$\n\nH. $h(x) = \\frac{x}{2},$ $x \\in [-2,7).$\n\nEnter the letters of the functions that have inverses, separated by commas.  For example, if you think functions $b(x)$ and $e(x)$ have inverses, enter \"B, E\" without the quotation marks.",
        "inference": "A. $a(x) = \\sqrt{2 - x},$ $x \\in (-\\infty,2].$  The function is strictly decreasing on $(-\\infty,2]$.  Thus, it is one-to-one and has an inverse.\n\nB. $b(x) = x^3 - x,$ $x \\in \\mathbb{R}.$ $b'(x) = 3x^2 - 1.$  The derivative is zero when $3x^2 - 1 = 0,$ i.e., $x = \\pm \\frac{1}{\\sqrt{3}}.$  The function is increasing on $\\left(-\\infty, -\\frac{1}{\\sqrt{3}}\\right]$ and $\\left[\\frac{1}{\\sqrt{3}},\\infty\\right)$, and decreasing on $\\left[-\\frac{1}{\\sqrt{3}},\\frac{1}{\\sqrt{3}}\\right).$  Thus, it is not one-to-one.\n\nC. $c(x) = x + \\frac{1}{x},$ $x \\in (0,\\infty).$  $c'(x) = 1 - \\frac{1}{x^2}.$  $c'(x) > 0$ for $x > 1$ and $c'(x) < 0$ for $0 < x < 1.$  The function is decreasing on $(0,1)$ and increasing on $(1,\\infty).$  Thus, it is not one-to-one.\n\nD. $d(x) = 2x^2 + 4x + 7,$ $x \\in [0,\\infty).$  $d'(x) = 4x + 4.$  $d'(x) > 0$ for $x > -1.$ Since the domain is $[0,\\infty)$, the function is strictly increasing. Thus, it is one-to-one.\n\nE. $e(x) = |x - 2| + |x + 3|,$ $x \\in \\mathbb{R}.$  The function is piecewise linear, but it's not strictly monotonic.  Thus, it is not one-to-one.\n\nF. $f(x) = 3^x + 7^x,$ $x \\in \\mathbb{R}.$  $f'(x) = 3^x \\ln 3 + 7^x \\ln 7 > 0,$ so $f(x)$ is increasing and thus one-to-one.\n\nG. $g(x) = x - \\frac{1}{x},$ $x \\in (0,\\infty).$  $g'(x) = 1 + \\frac{1}{x^2} > 0,$ so $g(x)$ is strictly increasing and thus one-to-one.\n\nH. $h(x) = \\frac{x}{2},$ $x \\in [-2,7).$  $h'(x) = \\frac{1}{2} > 0.$  The function is strictly increasing, and thus one-to-one.\n\nA, D, F, G, H have inverses.\n\nFinal Answer: $\\boxed{A, D, F, G, H}$",
        "ground_truth": "A. The function $a(x) = \\sqrt{2 - x}$ is decreasing, so it has an inverse.\n\nB. Note that $b(0) = b(1) = 0,$ so the function $b(x)$ does not have an inverse.\n\nC. Note that $c \\left( \\frac{1}{2} \\right) = c(2) = \\frac{5}{2},$ so the function $c(x)$ does not have an inverse.\n\nD. The function $d(x) = 2x^2 + 4x + 7 = 2(x + 1)^2 + 5$ is increasing on $[0,\\infty),$ so it has an inverse.\n\nE. Note that $e(2) = e(-3) = 5,$ so the function $e(x)$ does not have an inverse.\n\nF. Both $3^x$ and $7^x$ are increasing, so $f(x) = 3^x + 7^x$ is also increasing.  Hence, it has an inverse.\n\nG. Suppose $g(a) = g(b)$ for some $a,$ $b > 0.$  Then\n\\[a - \\frac{1}{a} = b - \\frac{1}{b}.\\]Multiplying both sides by $ab,$ we get\n\\[a^2 b - b = ab^2 - a.\\]Then $a^2 b - ab^2 + a - b = 0,$ which factors as $(a - b)(ab + 1) = 0.$  Since $a$ and $b$ are positive, $ab + 1$ cannot be 0, so $a = b.$\n\nWe have shown that $g(a) = g(b)$ forces $a = b,$ so the function $g(x)$ has an inverse.\n\nH. The function $h(x) = \\frac{x}{2}$ has an inverse, namely $h^{-1}(x) = 2x.$\n\nThus, the letters of the functions that have inverses are $\\boxed{\\text{A, D, F, G, H}}.$"
    },
    {
        "question": "A. $a(x) = \\sqrt{2 - x},$ $x \\in (-\\infty,2].$  The function is strictly decreasing on $(-\\infty,2]$.  Thus, it is one-to-one and has an inverse.\n\nB. $b(x) = x^3 - x,$ $x \\in \\mathbb{R}.$ $b'(x) = 3x^2 - 1.$  The derivative is zero when $3x^2 - 1 = 0,$ i.e., $x = \\pm \\frac{1}{\\sqrt{3}}.$  The function is increasing on $\\left(-\\infty, -\\frac{1}{\\sqrt{3}}\\right]$ and $\\left[\\frac{1}{\\sqrt{3}},\\infty\\right)$, and decreasing on $\\left[-\\frac{1}{\\sqrt{3}},\\frac{1}{\\sqrt{3}}\\right).$  Thus, it is not one-to-one.\n\nC. $c(x) = x + \\frac{1}{x},$ $x \\in (0,\\infty).$  $c'(x) = 1 - \\frac{1}{x^2}.$  $c'(x) > 0$ for $x > 1$ and $c'(x) < 0$ for $0 < x < 1.$  The function is decreasing on $(0,1)$ and increasing on $(1,\\infty).$  Thus, it is not one-to-one.\n\nD. $d(x) = 2x^2 + 4x + 7,$ $x \\in [0,\\infty).$  $d'(x) = 4x + 4.$  $d'(x) > 0$ for $x > -1.$ Since the domain is $[0,\\infty)$, the function is strictly increasing. Thus, it is one-to-one.\n\nE. $e(x) = |x - 2| + |x + 3|,$ $x \\in \\mathbb{R}.$  The function is piecewise linear, but it's not strictly monotonic.  Thus, it is not one-to-one.\n\nF. $f(x) = 3^x + 7^x,$ $x \\in \\mathbb{R}.$  $f'(x) = 3^x \\ln 3 + 7^x \\ln 7 > 0,$ so $f(x)$ is increasing and thus one-to-one.\n\nG. $g(x) = x - \\frac{1}{x},$ $x \\in (0,\\infty).$  $g'(x) = 1 + \\frac{1}{x^2} > 0,$ so $g(x)$ is strictly increasing and thus one-to-one.\n\nH. $h(x) = \\frac{x}{2},$ $x \\in [-2,7).$  $h'(x) = \\frac{1}{2} > 0.$  The function is strictly increasing, and thus one-to-one.\n\nA, D, F, G, H have inverses.\n\nFinal Answer: $\\boxed{A, D, F, G, H}$\nThere might be an error in the solution above because of lack of understanding of the question. Please correct the error, if any, and rewrite the solution. Only output the final solution \\\\boxed{$answer$}. I hope it is correct.'",
        "inference": "A, D, F, G, H\nFinal Answer: $\\boxed{A, D, F, G, H}$",
        "ground_truth": "A. The function $a(x) = \\sqrt{2 - x}$ is decreasing, so it has an inverse.\n\nB. Note that $b(0) = b(1) = 0,$ so the function $b(x)$ does not have an inverse.\n\nC. Note that $c \\left( \\frac{1}{2} \\right) = c(2) = \\frac{5}{2},$ so the function $c(x)$ does not have an inverse.\n\nD. The function $d(x) = 2x^2 + 4x + 7 = 2(x + 1)^2 + 5$ is increasing on $[0,\\infty),$ so it has an inverse.\n\nE. Note that $e(2) = e(-3) = 5,$ so the function $e(x)$ does not have an inverse.\n\nF. Both $3^x$ and $7^x$ are increasing, so $f(x) = 3^x + 7^x$ is also increasing.  Hence, it has an inverse.\n\nG. Suppose $g(a) = g(b)$ for some $a,$ $b > 0.$  Then\n\\[a - \\frac{1}{a} = b - \\frac{1}{b}.\\]Multiplying both sides by $ab,$ we get\n\\[a^2 b - b = ab^2 - a.\\]Then $a^2 b - ab^2 + a - b = 0,$ which factors as $(a - b)(ab + 1) = 0.$  Since $a$ and $b$ are positive, $ab + 1$ cannot be 0, so $a = b.$\n\nWe have shown that $g(a) = g(b)$ forces $a = b,$ so the function $g(x)$ has an inverse.\n\nH. The function $h(x) = \\frac{x}{2}$ has an inverse, namely $h^{-1}(x) = 2x.$\n\nThus, the letters of the functions that have inverses are $\\boxed{\\text{A, D, F, G, H}}.$"
    }
]